cloudml_hypertune-0.1.0.dev2.dist-info/DESCRIPTION.rst
cloudml_hypertune-0.1.0.dev2.dist-info/METADATA
cloudml_hypertune-0.1.0.dev2.dist-info/RECORD
cloudml_hypertune-0.1.0.dev2.dist-info/WHEEL
cloudml_hypertune-0.1.0.dev2.dist-info/metadata.json
cloudml_hypertune-0.1.0.dev2.dist-info/top_level.txt
hypertune/__init__.py
hypertune/hypertune.py
