Metadata-Version: 2.0
Name: cloudml-hypertune
Version: 0.1.0.dev2
Summary: A library to report Google CloudML Engine HyperTune metrics.
Home-page: http://pypi.python.org/pypi/hypertune/
Author: Google CloudML Engine
Author-email: cloudml-feedback@google.com
License: Apache Software License
Keywords: ml hyperparameter tuning
Platform: UNKNOWN
Classifier: Development Status :: 3 - Alpha
Classifier: Intended Audience :: Developers
Classifier: Topic :: Software Development :: Libraries :: Python Modules
Classifier: Topic :: Internet
Classifier: Topic :: Scientific/Engineering
Classifier: Topic :: System :: Distributed Computing
Classifier: License :: OSI Approved :: Apache Software License
Classifier: Programming Language :: Python
Classifier: Programming Language :: Python :: 2.7
Classifier: Programming Language :: Python :: 3.5
Classifier: Operating System :: POSIX
Classifier: Operating System :: MacOS
Classifier: Operating System :: Unix
